LICENSE
MANIFEST.in
README.md
requirements.txt
setup.py
version.py
lux.egg-info/PKG-INFO
lux.egg-info/SOURCES.txt
lux.egg-info/dependency_links.txt
lux.egg-info/requires.txt
lux.egg-info/top_level.txt