Metadata-Version: 2.1
Name: lux
Version: 0.5.1
Summary: A Python API for Intelligent Data Discovery
Home-page: https://github.com/lux-org/lux
Author: Doris Jung-Lin Lee
Author-email: dorisjunglinlee@gmail.com
License: Apache-2.0 License
Keywords: Visualization,Analytics,Data Science,Data Analysis
Platform: UNKNOWN
Classifier: Development Status :: 1 - Planning
Classifier: Intended Audience :: Developers
Classifier: Intended Audience :: Science/Research
Classifier: Intended Audience :: Other Audience
Classifier: Topic :: Scientific/Engineering :: Information Analysis
Classifier: Topic :: Scientific/Engineering :: Visualization
Classifier: License :: OSI Approved :: Apache Software License
Classifier: Programming Language :: Python :: 3
Requires-Python: >=3.5
Provides-Extra: test
